ipynote
