Metadata-Version: 2.1
Name: ipynote
Version: 0.0.3
Summary: a little note taking object inside ipython
Home-page: https://github.com/eaybek/ipynote
Author: Erdem Aybek
Author-email: eaybek@gmail.com
License: UNKNOWN
Platform: UNKNOWN
Classifier: Programming Language :: Python :: 3
Classifier: License :: OSI Approved :: MIT License
Classifier: Operating System :: POSIX :: Linux
Classifier: Development Status :: 1 - Planning
Requires-Python: >=3.6
